retail_stats/__init__.py
retail_stats/benchmark.py
retail_stats/elasticity.py
retail_stats-0.0.2.post1.dist-info/LICENSE
retail_stats-0.0.2.post1.dist-info/METADATA
retail_stats-0.0.2.post1.dist-info/WHEEL
retail_stats-0.0.2.post1.dist-info/top_level.txt
retail_stats-0.0.2.post1.dist-info/RECORD
