Metadata-Version: 2.1
Name: retail-stats
Version: 0.0.2.post1
Summary: A simple library to calculate price elasticity, cross elasticity
Home-page: https://github.com/insectatorious/retail-stats
Author: Sumanas Sarma
Author-email: insectatorious+pypi@gmail.com
License: UNKNOWN
Keywords: price-elasticity cross-elasticity sales-analysis
Platform: UNKNOWN
Classifier: Programming Language :: Python :: 3.7
Classifier: Programming Language :: Python :: 3.8
Classifier: Programming Language :: Python :: 3.9
Classifier: License :: OSI Approved :: GNU General Public License v3 (GPLv3)
Classifier: Operating System :: OS Independent
Classifier: Development Status :: 3 - Alpha
Classifier: Topic :: Office/Business
Classifier: Topic :: Office/Business :: Financial
Requires-Python: >=3.7
Requires-Dist: numpy (~=1.19)
